daphantom/__init__.py
daphantom/business/__init__.py
daphantom/business/alibaba_1688/__init__.py
daphantom/business/alibaba_1688/token_generate.py
daphantom/business/email/__init__.py
daphantom/business/email/email163.py
daphantom/business/walmart/__init__.py
daphantom/business/walmart/token_generate.py
daphantom/common/__init__.py
daphantom/common/components.py
daphantom/common/decorate.py
daphantom/common/error.py
daphantom/common/log.py
daphantom/common/requests4.py
daphantom/exceptions/__init__.py
daphantom/exceptions/mysqlerr.py
daphantom/exceptions/publicerr.py
daphantom/mysql_database/__init__.py
daphantom/mysql_database/basemodel.py
daphantom/redis_database/__init__.py
daphantom-0.0.3.dist-info/LICENSE
daphantom-0.0.3.dist-info/METADATA
daphantom-0.0.3.dist-info/WHEEL
daphantom-0.0.3.dist-info/top_level.txt
daphantom-0.0.3.dist-info/RECORD
