Metadata-Version: 2.1
Name: daphantom
Version: 0.0.3
Summary: Ghost Crawler Data Terminator - a stealthy web crawler framework by Xiaomu (小木).
Home-page: https://www.jiangongfang.top
Author: Xiaomu
Author-email: jiangongfang@foxmail.com
License: MIT
Classifier: Programming Language :: Python :: 3.8
Classifier: Programming Language :: Python :: 3.9
Classifier: Programming Language :: Python :: 3.10
Classifier: Programming Language :: Python :: 3.11
Classifier: Programming Language :: Python :: 3.12
Classifier: License :: OSI Approved :: MIT License
Classifier: Operating System :: OS Independent
Requires-Python: >=3.8
License-File: LICENSE
Requires-Dist: requests>=2.32.4
Requires-Dist: PySocks>=1.7.1
Requires-Dist: sqlalchemy>=2.0.38
Requires-Dist: loguru>=0.7.3
Requires-Dist: json5>=0.12.1
